MANIFEST.in
README.md
setup.py
speccer/__init__.py
speccer/indentation.py
speccer/processor.py
speccer/runner.py
speccer/statement.py
speccer/utils.py
speccer.egg-info/PKG-INFO
speccer.egg-info/SOURCES.txt
speccer.egg-info/dependency_links.txt
speccer.egg-info/entry_points.txt
speccer.egg-info/requires.txt
speccer.egg-info/top_level.txt