Metadata-Version: 1.0
Name: speccer
Version: 0.7.5
Summary: Specification based test runner.
Home-page: https://github.com/bebraw/speccer
Author: Juho Vepsäläinen
Author-email: bebraw@gmail.com
License: MIT
Platform: UNKNOWN
Classifier: Development Status :: 4 - Beta
Classifier: Environment :: Console
Classifier: Intended Audience :: Developers
Classifier: Intended Audience :: System Administrators
Classifier: License :: OSI Approved :: MIT License
Classifier: Operating System :: POSIX
Classifier: Programming Language :: Python
Classifier: Topic :: Software Development :: Testing
